Workbook

Sheet Question 16
A1: DATA FROM 10K FILING (IN MILLIONS)
A2: YEAR | B2: 2024 | C2: 2025
A4: FIXED ASSET | B4: =29032 -> 29032 | C4: =31909 -> 31909
A5: INVENTORY | B5: =18647 -> 18647 | C5: =18116 -> 18116
A6: ACCOUNTS RECEIVABLE | B6: =2721 -> 2721 | C6: =3203 -> 3203
A7: TOTAL ASSET | B7: =69831 -> 69831 | C7: =77099 -> 77099
A9: COST OF GOOD SOLD | B9: =222358 -> 222358 | C9: =239886 -> 239886
A10: TOTAL SALES (INCLUDING MEMBERSHIP FEE) | B10: =254453 -> 254453 | C10: =275235 -> 275235
A11: EBIT (OPERATING INCOME) | B11: =9285 -> 9285 | C11: =10383 -> 10383
A12: NET SALES | B12: =249625 -> 249625 | C12: =269912 -> 269912
A13: GROSS PROFIT | B13: =B12-B9 -> 27267 | C13: =C12-C9 -> 30026
A15: INTEREST EXPENSE | B15: =169 -> 169 | C15: =154 -> 154
A16: INTEREST INCOME | B16: =634 -> 634 | C16: =589 -> 589
A17: INCOME BEFORE INCOME TAX | B17: =9740 -> 9740 | C17: =10818 -> 10818
A18: NET INCOME | B18: =7367 -> 7367 | C18: =8099 -> 8099
A20: TOTAL STOCKHOLDER EQUITY | B20: =23622 -> 23622 | C20: =29164 -> 29164
A22: TOTAL DEBT | B22: =5919 -> 5919 | C22: =5805 -> 5805
A24: CASH EQUIVALENT | B24: =9906 -> 9906 | C24: =14161 -> 14161
A25: SHORT TERM INVESTMENTS | B25: =1238 -> 1238 | C25: =1123 -> 1123
A26: INVESTED CAPITAL | B26: =B25+B24+B22+B20 -> 40685 | C26: =C24+C22+C20+C25 -> 50253
A27: Tax rate | C27: =FCFF!N2 -> 0.25134036
A28: NOPAT | C28: =C11*(1-C27) -> 7773.3331
A30: QUESTION 16 A)
A31: ANALYZE THE COMPANY'S PROFITABILITY
A32: ROA:
A34: ROA = NET INCOME/ AVERAGE TOTAL ASSETS | B34: =C18/((B7+C7)/2) -> 0.11024297
H35: QUESTION 16 PART C)
A36: i) ROE (5 FACTOR DUPONT) :
J38: SAMPLE | K38: NET INCOME | L38: INCOME BEFORE TAX | M38: SALES | N38: AVERAGE TOTAL ASSETS | O38: AVERAGE TOTAL EQUITY | P38: EBIT | Q38: Current asset | R38: Current liabilities
A39: DuPont Analysis | B39: COSTCO | C39: INDUSTRY (Small sample) | J39: WMT US Equity | K39: =20157 -> 20157 | L39: =26309 -> 26309 | M39: =674538 -> 674538 | N39: =(260823+253399)/2 -> 257111 | O39: =(97421+90349)/2 -> 93885 | P39: =29348 -> 29348 | Q39: =79458 -> 79458 | R39: =96584 -> 96584
A40: NET INCOME/ INCOME BEFORE TAX | B40: =C18/C17 -> 0.74865964 | C40: =R60 -> 0.7693691 | J40: TGT US Equity | K40: =4091 -> 4091 | L40: =5261 -> 5261 | M40: =106566 -> 106566 | N40: =(57769+55356)/2 -> 56562.5 | O40: =(14666+13432)/2 -> 14049 | P40: =5566 -> 5566 | Q40: =19454 -> 19454 | R40: =20799 -> 20799
A41: INCOME BEFORE TAX/ EBIT | B41: =C17/C11 -> 1.0418954 | C41: =S60 -> 0.88457864
A42: EBIT/SALES | B42: =C11/C12 -> 0.038468093 | C42: =M60 -> 0.071554346 | J42: DLTR US Equity | K42: =1042.5 -> 1042.5 | L42: =1383.6 -> 1383.6 | M42: =17565.8 -> 17565.8 | N42: =(18644+22023.5)/2 -> 20333.75 | O42: =(3977.4+7313.1)/2 -> 5645.25 | P42: =1462 -> 1462 | Q42: =9107.2 -> 9107.2 | R42: =8585.9 -> 8585.9
A43: SALES/ TOTAL AVERAGE ASSETS | B43: =C12/((B7+C7)/2) -> 3.6740216 | C43: =N60 -> 1.880414 | J43: L CN Equity | K43: =2275 -> 2275 | L43: =3081 -> 3081 | M43: =61014 -> 61014 | N43: =(40880+38979)/2 -> 39929.5 | O43: =(11266+11619)/2 -> 11442.5 | P43: =3902 -> 3902 | Q43: =14548 -> 14548 | R43: =11768 -> 11768
A44: AVERAGE TOTAL ASSETS/ AVERAGE EQUITY | B44: =((B7+C7)/2)/((B20+C20)/2) -> 2.7835032 | C44: =O60 -> 3.650473 | J44: KR US Equity | K44: =2665 -> 2665 | L44: =3342 -> 3342 | M44: =147123 -> 147123 | N44: =(52616+50505)/2 -> 51560.5 | O44: =(8281+11601)/2 -> 9941 | P44: =3849 -> 3849 | Q44: =15273 -> 15273 | R44: =15940 -> 15940
J45: ACI US Equity | K45: =203118 -> 203118 | L45: =250409 -> 250409 | M45: =1594288 -> 1594288 | N45: =(3025293+3444739)/2 -> 3235016 | O45: =(1424327+1324297)/2 -> 1374312 | P45: =308135 -> 308135 | Q45: =990822 -> 990822 | R45: 602628
A47: ROE: | B47: =B40*B41*B42*B43*B44 -> 0.30686167 | J47: BJ US Equity | K47: =534417 -> 534417 | L47: =720847 -> 720847 | M47: =20045329 -> 20045329 | N47: =(7065305+6677622)/2 -> 6871463.5 | O47: =(1847454+1458851)/2 -> 1653152.5 | P47: =772206 -> 772206 | Q47: =1878960 -> 1878960 | R47: =2534082 -> 2534082
A49: EVA: | C49: =C28-(WACC!B99*B26) -> 7773.3331
J51: SAMPLE | K51: current ratio | L51: cash ratio | M51: EBIT/SALES | N51: SALES/ TOTAL AVERAGE ASSETS | O51: AVERAGE TOTAL ASSETS/ AVERAGE EQUITY | P51: ROE | Q51: Interest coverage ratio | R51: NET INCOME/INCOME BEFORE TAX | S51: INCOME BEFORE TAX/ EBIT
A52: ii) TURNOVER RATIOS | J52: WMT US Equity | K52: =Q39/R39 -> 0.82268285 | L52: =9037/R39 -> 0.093566222 | M52: =P39/M39 -> 0.043508298 | N52: =M39/N39 -> 2.6235284 | O52: =N39/O39 -> 2.7385738 | P52: =R52*S52*O52*N52*M52 -> 0.21469883 | Q52: =P39/2728 -> 10.758065 | R52: =K39/L39 -> 0.76616367 | S52: =L39/P39 -> 0.8964495
J53: TGT US Equity | K53: =Q40/R40 -> 0.93533343 | L53: =4762/R40 -> 0.22895332 | M53: =P40/M40 -> 0.052230543 | N53: =M40/N40 -> 1.8840398 | O53: =N40/O40 -> 4.0260873 | P53: =R53*S53*O53*N53*M53 -> 0.2911951 | Q53: =P40/411 -> 13.542579 | R53: =K40/L40 -> 0.77760882 | S53: =L40/P40 -> 0.94520302
A54: TOTAL ASSET TURNOVER | B54: =C12/((B7+C7)/2) -> 3.6740216
A55: FIXED ASSET TURNOVER | B55: =C12/((B4+C4)/2) -> 8.8581415 | J55: DLTR US Equity | K55: =Q42/R42 -> 1.0607158 | L55: =1256.5/R42 -> 0.14634459 | M55: =P42/M42 -> 0.083229913 | N55: =M42/N42 -> 0.8638741 | O55: =N42/O42 -> 3.601922 | P55: =R55*S55*O55*N55*M55 -> 0.18466853 | Q55: =P42/107.5 -> 13.6 | R55: =K42/L42 -> 0.75346921 | S55: =L42/P42 -> 0.94637483
A56: INVENTORY TURNOVER | B56: =C9/((B5+C5)/2) -> 13.050404 | J56: L CN Equity | K56: =Q43/R43 -> 1.2362339 | L56: =2110/R43 -> 0.1792998 | M56: =P43/M43 -> 0.063952535 | N56: =M43/N43 -> 1.5280432 | O56: =N43/O43 -> 3.4895783 | P56: =R56*S56*O56*N56*M56 -> 0.19882019 | Q56: =P43/821 -> 4.7527406 | R56: =K43/L43 -> 0.73839662 | S56: =L43/P43 -> 0.78959508
J57: KR US Equity | K57: =Q44/R44 -> 0.95815558 | L57: =3959/P44 -> 1.0285789 | M57: =P44/M44 -> 0.026161783 | N57: =M44/N44 -> 2.8534052 | O57: =N44/O44 -> 5.1866512 | P57: =R57*S57*O57*N57*M57 -> 0.26808168 | Q57: =P44/450 -> 8.5533333 | R57: =K44/L44 -> 0.79742669 | S57: =L44/P44 -> 0.86827747
J58: ACI US Equity | K58: =Q45/R45 -> 1.6441685 | L58: =216394/R45 -> 0.35908388 | M58: =P45/M45 -> 0.19327436 | N58: =M45/N45 -> 0.49282229 | O58: =N45/O45 -> 2.3539167 | P58: =R58*S58*O58*N58*M58 -> 0.14779613 | Q58: =P45/72471 -> 4.2518387 | R58: =K45/L45 -> 0.81114497 | S58: =L45/P45 -> 0.81266004
J59: BJ US Equity | K59: =Q47/R47 -> 0.74147561 | L59: =28272/R47 -> 0.011156703 | M59: =P47/M47 -> 0.03852299 | N59: =M47/N47 -> 2.9171848 | O59: =N47/O47 -> 4.1565817 | P59: =R59*S59*O59*N59*M59 -> 0.32327145 | Q59: =P47/51359 -> 15.035456 | R59: =K47/L47 -> 0.74137369 | S59: =L47/P47 -> 0.93349055
A60: iii) Profitability of sales | J60: AVERAGE | K60: =AVERAGE(K52:K59) -> 1.0569665 | L60: =AVERAGE(L52:L59) -> 0.29242619 | M60: =AVERAGE(M52:M59) -> 0.071554346 | N60: =AVERAGE(N52:N59) -> 1.880414 | O60: =AVERAGE(O52:O59) -> 3.650473 | P60: =AVERAGE(P52:P59) -> 0.23264742 | Q60: =AVERAGE(Q52:Q59) -> 10.070573 | R60: =AVERAGE(R52:R59) -> 0.7693691 | S60: =AVERAGE(S52:S59) -> 0.88457864
A61: GROSS PROFIT MARGIN | B61: =C13/C12 -> 0.11124366
A62: OPERATING PROFIT MARGIN | B62: =C11/C12 -> 0.038468093 | J62: COSTCO | K62: =B94 -> 1.0342783 | L62: =B96 -> 0.41187884 | M62: =B42 -> 0.038468093 | N62: =B43 -> 3.6740216 | O62: =B44 -> 2.7835032 | P62: =B47 -> 0.30686167 | Q62: =B85 -> 67.422078 | R62: =B40 -> 0.74865964 | S62: =B41 -> 1.0418954
A63: NET PROFIT MARGIN | B63: =C18/C10 -> 0.029425763
H65: comparison using a small | J65: SAMPLE | K65: ROE | L65: EBIT/SALES | M65: Interest coverage ratio | N65: AVERAGE TOTAL ASSETS/ AVERAGE EQUITY | O65: SALES/ TOTAL AVERAGE ASSETS | P65: cash ratio | Q65: current ratio
A66: Question 16 b) | C66: 2024 | D66: 2025 | H66: sample | J66: WMT US Equity | K66: =P52 -> 0.21469883 | L66: =M52 -> 0.043508298 | M66: =Q52 -> 10.758065 | N66: =O52 -> 2.7385738 | O66: =N52 -> 2.6235284 | P66: =L52 -> 0.093566222 | Q66: =K52 -> 0.82268285
B67: Cash | C67: =9906 -> 9906 | D67: =14161 -> 14161 | J67: TGT US Equity | K67: =P53 -> 0.2911951 | L67: =M53 -> 0.052230543 | M67: =Q53 -> 13.542579 | N67: =O53 -> 4.0260873 | O67: =N53 -> 1.8840398 | P67: =L53 -> 0.22895332 | Q67: =K53 -> 0.93533343
B68: Short term investments | C68: =1238 -> 1238 | D68: =1123 -> 1123 | L68: =B102 | M68: =B48 | N68: =B49 | O68: =B50 | P68: =B53 | Q68: =B91 | R68: =B46
B69: Receivables net | C69: =2721 -> 2721 | D69: =3203 -> 3203 | J69: DLTR US Equity | K69: =P55 -> 0.18466853 | L69: =M55 -> 0.083229913 | M69: =Q55 -> 13.6 | N69: =O55 -> 3.601922 | O69: =N55 -> 0.8638741 | P69: =L55 -> 0.14634459 | Q69: =K55 -> 1.0607158
B70: Merchandise Inventory | C70: =18647 -> 18647 | D70: =18116 -> 18116 | J70: L CN Equity | K70: =P56 -> 0.19882019 | L70: =M56 -> 0.063952535 | M70: =Q56 -> 4.7527406 | N70: =O56 -> 3.4895783 | O70: =N56 -> 1.5280432 | P70: =L56 -> 0.1792998 | Q70: =K56 -> 1.2362339
B71: Other Current assets | C71: =1734 -> 1734 | D71: =1777 -> 1777 | J71: KR US Equity | K71: =P57 -> 0.26808168 | L71: =M57 -> 0.026161783 | M71: =Q57 -> 8.5533333 | N71: =O57 -> 5.1866512 | O71: =N57 -> 2.8534052 | P71: =L57 -> 1.0285789 | Q71: =K57 -> 0.95815558
B72: Total Current Assets | C72: =SUM(C67:C71) -> 34246 | D72: =SUM(D67:D71) -> 38380 | J72: ACI US Equity | K72: =P58 -> 0.14779613 | L72: =M58 -> 0.19327436 | M72: =Q58 -> 4.2518387 | N72: =O58 -> 2.3539167 | O72: =N58 -> 0.49282229 | P72: =L58 -> 0.35908388 | Q72: =K58 -> 1.6441685
J73: BJ US Equity | K73: =P59 -> 0.32327145 | L73: =M59 -> 0.03852299 | M73: =Q59 -> 15.035456 | N73: =O59 -> 4.1565817 | O73: =N59 -> 2.9171848 | P73: =L59 -> 0.011156703 | Q73: =K59 -> 0.74147561
J74: AVERAGE | K74: =AVERAGE(K66:K73) -> 0.23264742 | L74: =AVERAGE(L66:L73) -> 0.071554346 | M74: =AVERAGE(M66:M73) -> 10.070573 | N74: =AVERAGE(N66:N73) -> 3.650473 | O74: =AVERAGE(O66:O73) -> 1.880414 | P74: =AVERAGE(P66:P73) -> 0.29242619 | Q74: =AVERAGE(Q66:Q73) -> 1.0569665
B75: A/P | C75: =19421 -> 19421 | D75: =19783 -> 19783
B76: Accrued Salaries and Benefits | C76: =4794 -> 4794 | D76: =5205 -> 5205 | J76: COSTCO | K76: =P62 -> 0.30686167 | L76: =M62 -> 0.038468093 | M76: =Q62 -> 67.422078 | N76: =O62 -> 2.7835032 | O76: =N62 -> 3.6740216 | P76: =L62 -> 0.41187884 | Q76: =K62 -> 1.0342783
B77: Accrued Member reward | C77: =2435 -> 2435 | D77: =2677 -> 2677
B78: Deferred membership fee | C78: =2501 -> 2501 | D78: =2854 -> 2854
B79: Other Current Liabilities | C79: =6313 -> 6313 | D79: =6589 -> 6589 | H79: industry comparison with a bigger sample (data obtained from Bloomberg)
B80: Total Current Liabilities | C80: =SUM(C75:C79) -> 35464 | D80: =SUM(D75:D79) -> 37108
J81: SAMPLE | K81: ROE | L81: EBIT/SALES | M81: Interest coverage ratio | N81: AVERAGE TOTAL ASSETS/ AVERAGE EQUITY | O81: SALES/ TOTAL AVERAGE ASSETS | P81: cash ratio | Q81: current ratio
A82: i) | J82: WMT US Equity | K82: =K66 -> 0.21469883 | L82: =L66 -> 0.043508298 | M82: =M66 -> 10.758065 | N82: =N66 -> 2.7385738 | O82: =O66 -> 2.6235284 | P82: =P66 -> 0.093566222 | Q82: =Q66 -> 0.82268285
J83: TGT US Equity | K83: =K67 -> 0.2911951 | L83: =L67 -> 0.052230543 | M83: =M67 -> 13.542579 | N83: =N67 -> 4.0260873 | O83: =O67 -> 1.8840398 | P83: =P67 -> 0.22895332 | Q83: =Q67 -> 0.93533343
A84: DSCR | B84: =(C11+2426)/(C15+103) -> 49.840467 | C84: DEPRECIATION AND AMORTIZATION = 2426, REPAYMENT OF LONG TERM DEBT IS 103 | J84: DLTR US Equity | K84: =K69 -> 0.18466853 | L84: =L69 -> 0.083229913 | M84: =M69 -> 13.6 | N84: =N69 -> 3.601922 | O84: =O69 -> 0.8638741 | P84: =P69 -> 0.14634459 | Q84: =Q69 -> 1.0607158
A85: Interest Coverage ratio | B85: =C11/C15 -> 67.422078 | J85: L CN Equity | K85: =K70 -> 0.19882019 | L85: =L70 -> 0.063952535 | M85: =M70 -> 4.7527406 | N85: =N70 -> 3.4895783 | O85: =O70 -> 1.5280432 | P85: =P70 -> 0.1792998 | Q85: =Q70 -> 1.2362339
J86: KR US Equity | K86: =K71 -> 0.26808168 | L86: =L71 -> 0.026161783 | M86: =M71 -> 8.5533333 | N86: =N71 -> 5.1866512 | O86: =O71 -> 2.8534052 | P86: =P71 -> 1.0285789 | Q86: =Q71 -> 0.95815558
A87: Debt to equity ratio | B87: =F92/F93 -> 1.643636 | J87: ACI US Equity | K87: =K72 -> 0.14779613 | L87: =L72 -> 0.19327436 | M87: =M72 -> 4.2518387 | N87: =N72 -> 2.3539167 | O87: =O72 -> 0.49282229 | P87: =P72 -> 0.35908388 | Q87: =Q72 -> 1.6441685
A88: Debt ratio | B88: =((E92+F92)/2)/((B7+C7)/2) -> 0.64074049 | J88: BJ US Equity | K88: =K73 -> 0.32327145 | L88: =L73 -> 0.03852299 | M88: =M73 -> 15.035456 | N88: =N73 -> 4.1565817 | O88: =O73 -> 2.9171848 | P88: =P73 -> 0.011156703 | Q88: =Q73 -> 0.74147561
A89: Debt to capital Ratio | B89: =5788/(5788+F93) -> 0.16559854 | E89: 2024 | F89: 2025 | J89: AD NA Equity | K89: 0.14644173 | L89: 0.031155925 | M89: 3.6535433 | N89: 0.30311149 | O89: 1.90679 | P89: 0.37321069 | Q89: 0.83506755
J90: WOW AU Equity | K90: 0.18757304 | L90: 0.031573461 | M90: 2.4840547 | N90: 0.15152365 | O90: 2.0387221 | P90: 0.10368382 | Q90: 0.56851264
A91: ii) | J91: 139480 KS Equity | K91: -0.028335107 | L91: 0.00162292 | M91: 0.089717081 | N91: 0.32421768 | O91: 0.8359385 | P91: 0.15852112 | Q91: 0.96529237
D92: Total Liability | E92: =46209 -> 46209 | F92: =47935 -> 47935 | J92: WES AU Equity | K92: 0.32924497 | L92: 0.092659104 | M92: 10.657431 | N92: 0.32146862 | O92: 1.6517273 | P92: 0.07660903 | Q92: 1.1927233
D93: Stockholder Equity | E93: =B20 -> 23622 | F93: =C20 -> 29164 | J93: CENCOSUD CI Equity | K93: 0.043646693 | L93: 0.064881839 | M93: 3.5615606 | N93: 0.28896362 | O93: 1.1586315 | P93: 0.21732123 | Q93: 0.91758319
A94: Current ratio | B94: =D72/D80 -> 1.0342783 | J94: PCOPLN EU Equity | K94: -1.2033072 | L94: -0.072183415 | M94: -3.0677946 | N94: 0.19236038 | O94: 1.5968052 | P94: 0.19957387 | Q94: 0.95281779
A95: quick ratio | B95: =(D67+D68+D69)/D80 -> 0.49819446 | J95: EMP/A CN Equity | K95: 0.12971351 | L95: 0.041212392 | M95: 4.0407524 | N95: 0.31799239 | O95: 1.8430707 | P95: 0.069580078 | Q95: 0.76513672
A96: cash ratio | B96: =(D67+D68)/D80 -> 0.41187884 | J96: TSCO LN Equity | K96: 0.13619111 | L96: 0.038775102 | M96: 3.4316456 | N96: 0.27158468 | O96: 1.6350021 | P96: 0.33494935 | Q96: 0.64081042
A97: Non Cash Working Capital | B97: =(D69+D70)-D75 -> 1536 | J97: SBRY LN Equity | K97: 0.050899585 | L97: 0.027550896 | M97: 2.5828571 | N97: 0.27196282 | O97: 1.5042603 | P97: 0.24314619 | Q97: 0.74003679
J98: JMT PL Equity | K98: 0.20776292 | L98: 0.031974659 | M98: 1.9669118 | N98: 0.19662769 | O98: 3.0573127 | P98: 0.23026399 | Q98: 0.61058482
J99: DIA SM Equity | L99: -0.0006447 | M99: -0.037260549 | N99: -0.021444503 | P99: 0.23091802 | Q99: 0.54780947
J100: AXFO SS Equity | K100: 0.31101038 | L100: 0.039829641 | M100: 8.0095694 | N100: 0.21283422 | O100: 2.6919742 | P100: 0.055825611 | Q100: 0.66876804
A101: ROIC | J101: DNP PW Equity | K101: 0.21607443 | L101: 0.065189026 | M101: 15.858478 | N101: 0.54155193 | O101: 2.5862158 | P101: 0.16591326 | Q101: 0.82473352
A102: All in thousands | J102: COLR BB Equity | K102: 0.10630318 | L102: 0.040717296 | M102: 26.105263 | N102: 0.4868095 | O102: 1.6820319 | P102: 0.29334464 | Q102: 0.89732938
A103: After-tax OI | B103: =FCFF!B17 -> 7875600 | J103: SON PL Equity | K103: 0.080055351 | L103: 0.033900542 | M103: 1.1948854 | N103: 0.30170484 | O103: 1.2345883 | P103: 0.18098862 | Q103: 0.76296139
A104: Reinvestment | B104: =FCFF!B20+FCFF!B29 -> 2661000 | J104: 8267 JT Equity | K104: 0.024341596 | L104: 0.023458304 | M104: 5.5133575 | N104: 0.079175996 | O104: 0.72977181 | P104: 0.25258161 | Q104: 1.0295918
A105: Reinvestment Rate | B105: =B104/B103 -> 0.33787902 | J105: 7532 JP Equity | K105: 0.1685188 | L105: 0.072235639 | M105: 25.346869 | N105: 0.38072616 | O105: 1.5394916 | P105: 0.38340055 | Q105: 1.1956485
J106: 023530 KS Equity | K106: -0.083400829 | L106: 0.033826284 | M106: 0.69904007 | N106: 0.35891293 | O106: 0.39595123 | P106: 0.23552607 | Q106: 0.56089001
A107: Adjusted book value of debt | B107: =(5805000)+2668000 -> 8473000 | C107: from wacc | J107: CRC TB Equity | K107: 0.10418827 | L107: 0.064704358 | M107: 2.2667736 | N107: 0.23529767 | O107: 0.86167841 | P107: 0.070807706 | Q107: 0.58053326
A108: Book value of Equity | B108: 29164000 | C108: 10-k balance sheet | J108: 6808 HK Equity | K108: 0.003830935 | L108: 0.014898256 | M108: 2.6987342 | N108: 0.35562354 | O108: 1.164793 | P108: 0.43018487 | Q108: 0.961561
A109: Excess Cash | B109: =14161000-13335000 -> 826000 | C109: 10-k balance sheet | J109: 601933 CH Equity | K109: -0.44223045 | L109: -0.009947647 | M109: -0.60945728 | N109: 0.1094774 | O109: 1.4500026 | P109: 0.31378069 | Q109: 0.75995482
A110: Invested capital | B110: =B107+B108-B109 -> 36811000 | J110: COL AU Equity | K110: 0.29071804 | L110: 0.046800189 | M110: 4.0584795 | N110: 0.18481725 | O110: 2.2152674 | P110: 0.10282964 | Q110: 0.60939323
J111: MTS AU Equity | K111: 0.18030231 | L111: 0.02823414 | M111: 2.9877825 | N111: 0.24766521 | O111: 2.730504 | P111: 0.023331316 | Q111: 1.0393716
A112: ROIC | B112: =B103/B110 -> 0.21394692 | J112: WALMEX* MM Equity | K112: 0.2313756 | L112: 0.080707755 | M112: 9.0020518 | N112: 0.46425525 | O112: 2.0372535 | P112: 0.21378759 | Q112: 1.0152437
J113: SORIANAB MM Equity | K113: 0.046745101 | L113: 0.048371968 | M113: 2.6127865 | N113: 0.52263617 | O113: 1.1556564 | P113: 0.23883452 | Q113: 1.2353569
...

Sheet Trend Analysis
A1: Date | B1: Adj Close | C1: Ln Price | D1: Monthly Log Returns
A2: 44136 | B2: 361.22 | C2: =IF(B2<>"",LN(B2),"") -> 5.8894872 | D2: =IF(AND(B3<>"",B2<>""),LN(B3/B2),"") -> -0.039010337 | F2: # of Observations | G2: =COUNT(D:D) -> 61 | I2: Inputs
A3: 44166 | B3: 347.4 | C3: =IF(B3<>"",LN(B3),"") -> 5.8504769 | D3: =IF(AND(B4<>"",B3<>""),LN(B4/B3),"") -> -0.040953936 | F3: Mean monthly return (μ_monthly) | G3: =AVERAGE(D:D) -> 0.015416279 | I3: Last Price P₀ | J3: Annual Drift μ | K3: Annual Volatility σ | L3: Forecast Horizon (Years) | M3: Number of Steps
A4: 44197 | B4: 333.46 | C4: =IF(B4<>"",LN(B4),"") -> 5.8095229 | D4: =IF(AND(B5<>"",B4<>""),LN(B5/B4),"") -> -0.062744813 | F4: Monthly Volatility | G4: =_xlfn.STDEV.S(D:D) -> 0.066287914 | I4: =G7 -> 925.08 | J4: =G5 -> 0.18499535 | K4: =G6 -> 0.22962807 | L4: 2 | M4: 24
A5: 44228 | B5: 313.18 | C5: =IF(B5<>"",LN(B5),"") -> 5.7467781 | D5: =IF(AND(B6<>"",B5<>""),LN(B6/B5),"") -> 0.06487174 | F5: Annual Drift μ | G5: =12*G3 -> 0.18499535
A6: 44256 | B6: 334.17 | C6: =IF(B6<>"",LN(B6),"") -> 5.8116498 | D6: =IF(AND(B7<>"",B6<>""),LN(B7/B6),"") -> 0.054138093 | F6: Annual Volatility σ | G6: =SQRT(12)*G4 -> 0.22962807 | I6: Bull Market
A7: 44287 | B7: 352.76 | C7: =IF(B7<>"",LN(B7),"") -> 5.8657879 | D7: =IF(AND(B8<>"",B7<>""),LN(B8/B7),"") -> 0.018592385 | F7: Last Price P0 | G7: =B63 -> 925.08 | I7: Last Price P₀ | J7: Annual Drift μ | K7: Annual Volatility σ | L7: Forecast Horizon (Years) | M7: Number of Steps
A8: 44317 | B8: 359.38 | C8: =IF(B8<>"",LN(B8),"") -> 5.8843803 | D8: =IF(AND(B9<>"",B8<>""),LN(B9/B8),"") -> 0.04499603 | I8: =I4 -> 925.08 | J8: 0.23 | L8: 2 | M8: 24
A9: 44348 | B9: 375.92 | C9: =IF(B9<>"",LN(B9),"") -> 5.9293764 | D9: =IF(AND(B10<>"",B9<>""),LN(B10/B9),"") -> 0.082552365 | F9: https://finance.yahoo.com/quote/COST/
A10: 44378 | B10: 408.27 | C10: =IF(B10<>"",LN(B10),"") -> 6.0119287 | D10: =IF(AND(B11<>"",B10<>""),LN(B11/B10),"") -> 0.060101475 | I10: Bear Market
A11: 44409 | B11: 433.56 | C11: =IF(B11<>"",LN(B11),"") -> 6.0720302 | D11: =IF(AND(B12<>"",B11<>""),LN(B12/B11),"") -> -0.013561419 | I11: Last Price P₀ | J11: Annual Drift μ | K11: Annual Volatility σ | L11: Forecast Horizon (Years) | M11: Number of Steps
A12: 44440 | B12: 427.72 | C12: =IF(B12<>"",LN(B12),"") -> 6.0584688 | D12: =IF(AND(B13<>"",B12<>""),LN(B13/B12),"") -> 0.089721704 | I12: =I8 -> 925.08 | J12: 0.12 | L12: 2 | M12: 24
A13: 44470 | B13: 467.87 | C13: =IF(B13<>"",LN(B13),"") -> 6.1481905 | D13: =IF(AND(B14<>"",B13<>""),LN(B14/B13),"") -> 0.094499603
A14: 44501 | B14: 514.24 | C14: =IF(B14<>"",LN(B14),"") -> 6.2426901 | D14: =IF(AND(B15<>"",B14<>""),LN(B15/B14),"") -> 0.051172721
A15: 44531 | B15: 541.24 | C15: =IF(B15<>"",LN(B15),"") -> 6.2938628 | D15: =IF(AND(B16<>"",B15<>""),LN(B16/B15),"") -> -0.11676967 | I15: Forecast | L15: BULL | O15: BEAR
A16: 44562 | B16: 481.59 | C16: =IF(B16<>"",LN(B16),"") -> 6.1770931 | D16: =IF(AND(B17<>"",B16<>""),LN(B17/B16),"") -> 0.027565638
A17: 44593 | B17: 495.05 | C17: =IF(B17<>"",LN(B17),"") -> 6.2046588 | D17: =IF(AND(B18<>"",B17<>""),LN(B18/B17),"") -> 0.10496856 | I17: Time (Years) | J17: Forecasted Price | L17: Time (Years) | M17: Forecasted Price | O17: Time (Years) | P17: Forecasted Price
A18: 44621 | B18: 549.84 | C18: =IF(B18<>"",LN(B18),"") -> 6.3096273 | D18: =IF(AND(B19<>"",B18<>""),LN(B19/B18),"") -> -0.079716908 | I18: 0 | J18: =I4 -> 925.08 | L18: 0 | M18: =I4 -> 925.08 | O18: 0 | P18: =I12 -> 925.08
A19: 44652 | B19: 507.71 | C19: =IF(B19<>"",LN(B19),"") -> 6.2299104 | D19: =IF(AND(B20<>"",B19<>""),LN(B20/B19),"") -> -0.12983813 | I19: =($L$4/$M$4)+I18 -> 0.083333333 | J19: =$I$4 * EXP($J$4 *I19 ) -> 939.45179 | L19: =($L$4/$M$4)+L18 -> 0.083333333 | M19: =$I$8 * EXP($J$8 *L19 ) -> 942.98171 | O19: =($L$4/$M$4)+O18 -> 0.083333333 | P19: =$I$12 * EXP($J$12 *O19 ) -> 934.37721
A20: 44682 | B20: 445.89 | C20: =IF(B20<>"",LN(B20),"") -> 6.1000723 | D20: =IF(AND(B21<>"",B20<>""),LN(B21/B20),"") -> 0.02762625 | I20: =($L$4/$M$4)+I19 -> 0.16666667 | J20: =$I$4 * EXP($J$4 *I20 ) -> 954.04685 | L20: =($L$4/$M$4)+L19 -> 0.16666667 | M20: =$I$8 * EXP($J$8 *L20 ) -> 961.22985 | O20: =($L$4/$M$4)+O19 -> 0.16666667 | P20: =$I$12 * EXP($J$12 *O20 ) -> 943.76786
A21: 44713 | B21: 458.38 | C21: =IF(B21<>"",LN(B21),"") -> 6.1276985 | D21: =IF(AND(B22<>"",B21<>""),LN(B22/B21),"") -> 0.12169739 | I21: =($L$4/$M$4)+I20 -> 0.25 | J21: =$I$4 * EXP($J$4 *I21 ) -> 968.86866 | L21: =($L$4/$M$4)+L20 -> 0.25 | M21: =$I$8 * EXP($J$8 *L21 ) -> 979.83111 | O21: =($L$4/$M$4)+O20 -> 0.25 | P21: =$I$12 * EXP($J$12 *O21 ) -> 953.25288
A22: 44743 | B22: 517.7 | C22: =IF(B22<>"",LN(B22),"") -> 6.2493959 | D22: =IF(AND(B23<>"",B22<>""),LN(B23/B22),"") -> -0.034387905 | I22: =($L$4/$M$4)+I21 -> 0.33333333 | J22: =$I$4 * EXP($J$4 *I22 ) -> 983.92073 | L22: =($L$4/$M$4)+L21 -> 0.33333333 | M22: =$I$8 * EXP($J$8 *L22 ) -> 998.79234 | O22: =($L$4/$M$4)+O21 -> 0.33333333 | P22: =$I$12 * EXP($J$12 *O22 ) -> 962.83323
A23: 44774 | B23: 500.2 | C23: =IF(B23<>"",LN(B23),"") -> 6.215008 | D23: =IF(AND(B24<>"",B23<>""),LN(B24/B23),"") -> -0.10030866 | I23: =($L$4/$M$4)+I22 -> 0.41666667 | J23: =$I$4 * EXP($J$4 *I23 ) -> 999.20665 | L23: =($L$4/$M$4)+L22 -> 0.41666667 | M23: =$I$8 * EXP($J$8 *L23 ) -> 1018.1205 | O23: =($L$4/$M$4)+O22 -> 0.41666667 | P23: =$I$12 * EXP($J$12 *O23 ) -> 972.50987
A24: 44805 | B24: 452.46 | C24: =IF(B24<>"",LN(B24),"") -> 6.1146994 | D24: =IF(AND(B25<>"",B24<>""),LN(B25/B24),"") -> 0.060044617 | I24: =($L$4/$M$4)+I23 -> 0.5 | J24: =$I$4 * EXP($J$4 *I24 ) -> 1014.7301 | L24: =($L$4/$M$4)+L23 -> 0.5 | M24: =$I$8 * EXP($J$8 *L24 ) -> 1037.8227 | O24: =($L$4/$M$4)+O23 -> 0.5 | P24: =$I$12 * EXP($J$12 *O24 ) -> 982.28375
A25: 44835 | B25: 480.46 | C25: =IF(B25<>"",LN(B25),"") -> 6.174744 | D25: =IF(AND(B26<>"",B25<>""),LN(B26/B25),"") -> 0.074381482 | I25: =($L$4/$M$4)+I24 -> 0.58333333 | J25: =$I$4 * EXP($J$4 *I25 ) -> 1030.4946 | L25: =($L$4/$M$4)+L24 -> 0.58333333 | M25: =$I$8 * EXP($J$8 *L25 ) -> 1057.9061 | O25: =($L$4/$M$4)+O24 -> 0.58333333 | P25: =$I$12 * EXP($J$12 *O25 ) -> 992.15587
A26: 44866 | B26: 517.56 | C26: =IF(B26<>"",LN(B26),"") -> 6.2491255 | D26: =IF(AND(B27<>"",B26<>""),LN(B27/B26),"") -> -0.16658697 | I26: =($L$4/$M$4)+I25 -> 0.66666667 | J26: =$I$4 * EXP($J$4 *I26 ) -> 1046.5041 | L26: =($L$4/$M$4)+L25 -> 0.66666667 | M26: =$I$8 * EXP($J$8 *L26 ) -> 1078.3782 | O26: =($L$4/$M$4)+O25 -> 0.66666667 | P26: =$I$12 * EXP($J$12 *O26 ) -> 1002.1272
A27: 44896 | B27: 438.14 | C27: =IF(B27<>"",LN(B27),"") -> 6.0825385 | D27: =IF(AND(B28<>"",B27<>""),LN(B28/B27),"") -> 0.11304987 | I27: =($L$4/$M$4)+I26 -> 0.75 | J27: =$I$4 * EXP($J$4 *I27 ) -> 1062.7623 | L27: =($L$4/$M$4)+L26 -> 0.75 | M27: =$I$8 * EXP($J$8 *L27 ) -> 1099.2465 | O27: =($L$4/$M$4)+O26 -> 0.75 | P27: =$I$12 * EXP($J$12 *O27 ) -> 1012.1987
A28: 44927 | B28: 490.58 | C28: =IF(B28<>"",LN(B28),"") -> 6.1955884 | D28: =IF(AND(B29<>"",B28<>""),LN(B29/B28),"") -> -0.054196328 | I28: =($L$4/$M$4)+I27 -> 0.83333333 | J28: =$I$4 * EXP($J$4 *I28 ) -> 1079.2731 | L28: =($L$4/$M$4)+L27 -> 0.83333333 | M28: =$I$8 * EXP($J$8 *L28 ) -> 1120.5186 | O28: =($L$4/$M$4)+O27 -> 0.83333333 | P28: =$I$12 * EXP($J$12 *O28 ) -> 1022.3715
A29: 44958 | B29: 464.7 | C29: =IF(B29<>"",LN(B29),"") -> 6.141392 | D29: =IF(AND(B30<>"",B29<>""),LN(B30/B29),"") -> 0.027611818 | I29: =($L$4/$M$4)+I28 -> 0.91666667 | J29: =$I$4 * EXP($J$4 *I29 ) -> 1096.0404 | L29: =($L$4/$M$4)+L28 -> 0.91666667 | M29: =$I$8 * EXP($J$8 *L29 ) -> 1142.2023 | O29: =($L$4/$M$4)+O28 -> 0.91666667 | P29: =$I$12 * EXP($J$12 *O29 ) -> 1032.6465
A30: 44986 | B30: 477.71 | C30: =IF(B30<>"",LN(B30),"") -> 6.1690039 | D30: =IF(AND(B31<>"",B30<>""),LN(B31/B30),"") -> 0.012709083 | I30: =($L$4/$M$4)+I29 -> 1 | J30: =$I$4 * EXP($J$4 *I30 ) -> 1113.0681 | L30: =($L$4/$M$4)+L29 -> 1 | M30: =$I$8 * EXP($J$8 *L30 ) -> 1164.3057 | O30: =($L$4/$M$4)+O29 -> 1 | P30: =$I$12 * EXP($J$12 *O30 ) -> 1043.0248
... A42: 45352 | B42: 725.66 | C42: =IF(B42<>"",LN(B42),"") -> 6.5870816 | D42: =IF(AND(B43<>"",B42<>""),LN(B43/B42),"") -> -0.013373486 | I42: =($L$4/$M$4)+I41 -> 2 | J42: =$I$4 * EXP($J$4 *I42 ) -> 1339.2579 | L42: =($L$4/$M$4)+L41 -> 2 | M42: =$I$8 * EXP($J$8 *L42 ) -> 1465.3952 | O42: =($L$4/$M$4)+O41 -> 2 | P42: =$I$12 * EXP($J$12 *O42 ) -> 1176.0072
A43: 45383 | B43: 716.02 | C43: =IF(B43<>"",LN(B43),"") -> 6.5737081 | D43: =IF(AND(B44<>"",B43<>""),LN(B44/B43),"") -> 0.11523175
A44: 45413 | B44: 803.47 | C44: =IF(B44<>"",LN(B44),"") -> 6.6889398 | D44: =IF(AND(B45<>"",B44<>""),LN(B45/B44),"") -> 0.048335485
A45: 45444 | B45: 843.26 | C45: =IF(B45<>"",LN(B45),"") -> 6.7372753 | D45: =IF(AND(B46<>"",B45<>""),LN(B46/B45),"") -> -0.033486173
A46: 45474 | B46: 815.49 | C46: =IF(B46<>"",LN(B46),"") -> 6.7037892 | D46: =IF(AND(B47<>"",B46<>""),LN(B47/B46),"") -> 0.083570925
A47: 45505 | B47: 886.57 | C47: =IF(B47<>"",LN(B47),"") -> 6.7873601 | D47: =IF(AND(B48<>"",B47<>""),LN(B48/B47),"") -> -0.0065862674
A48: 45536 | B48: 880.75 | C48: =IF(B48<>"",LN(B48),"") -> 6.7807738 | D48: =IF(AND(B49<>"",B48<>""),LN(B49/B48),"") -> -0.014017746
A49: 45566 | B49: 868.49 | C49: =IF(B49<>"",LN(B49),"") -> 6.7667561 | D49: =IF(AND(B50<>"",B49<>""),LN(B50/B49),"") -> 0.10594182
A50: 45597 | B50: 965.55 | C50: =IF(B50<>"",LN(B50),"") -> 6.8726979 | D50: =IF(AND(B51<>"",B50<>""),LN(B51/B50),"") -> -0.057595322
A51: 45627 | B51: 911.51 | C51: =IF(B51<>"",LN(B51),"") -> 6.8151026 | D51: =IF(AND(B52<>"",B51<>""),LN(B52/B51),"") -> 0.067119498
A52: 45658 | B52: 974.79 | C52: =IF(B52<>"",LN(B52),"") -> 6.8822221 | D52: =IF(AND(B53<>"",B52<>""),LN(B53/B52),"") -> 0.06779737
A53: 45689 | B53: 1043.17 | C53: =IF(B53<>"",LN(B53),"") -> 6.9500194 | D53: =IF(AND(B54<>"",B53<>""),LN(B54/B53),"") -> -0.1021097
A54: 45717 | B54: 941.91 | C54: =IF(B54<>"",LN(B54),"") -> 6.8479097 | D54: =IF(AND(B55<>"",B54<>""),LN(B55/B54),"") -> 0.050229464
... A63: 45974 | B63: 925.08 | C63: =IF(B63<>"",LN(B63),"") -> 6.8298802 | D63: =IF(AND(B64<>"",B63<>""),LN(B64/B63),"")
C64: =IF(B64<>"",LN(B64),"") | D64: =IF(AND(B65<>"",B64<>""),LN(B65/B64),"")
C65: =IF(B65<>"",LN(B65),"") | D65: =IF(AND(B66<>"",B65<>""),LN(B66/B65),"")

Sheet Industry ROE
A2: IBISWorld Report - Info | C2: https://my-ibisworld-com.lib-ezproxy.concordia.ca/us/en/industry/45291/at-a-glance
B4: 2019 | C4: 2020 | D4: 2021 | E4: 2022 | F4: 2023 | G4: 3-year average | H4: 5-year average | I4: 10-year average
A5: Return in Net Worth (ROE) in % | B5: 0.236 | C5: 0.077 | D5: 0.073 | E5: 0.168 | F5: 0.303 | G5: 0.235 | H5: 0.155 | I5: 0.123
A9: Revenue growth: | B9: 2020–2025 CAGR | C9: 0.031
B10: 2025–2030 CAGR: 2.0% → slower growth reflecting mature market conditions. | C10: 0.02
A12: GDP growth - USD
A13: Q1-2026 | B13: 23778.89 | D13: CAGR of GDP | E13: =(((B14/B13)^(1/B15)))-1 -> 0.021109699
A14: Q1-2031 | B14: 26396.94
A15: n (years) | B15: 5
A17: data from: https://fred.stlouisfed.org/series/GDPPOT

Sheet WACC
A2: Cost of Debt
A3: Marginal Tax Rate | B3: =0.25 -> 0.25 | D3: on yahoo: tax provision/pretax income = 2,719,000/10,818,000
A4: Risk free rate | B4: 0.04067 | C4: CNBC US 10Y Treasury as of Nov 12 2025
A5: Company Default spread | B5: 0.0048 | C5: As of Tues, Nov 11 2025 | D5: https://fred.stlouisfed.org/series/BAMLC0A2CAA#:~:text=Rates%20%3E%20Corporate%20Bonds-,ICE%20BofA%20AA%20US%20Corporate%20Index%20Option%2DAdjusted%20Spread%20(BAMLC0A2CAA,Release%20Date:%20Nov%2011%2C%202025
A6: Country Default Spread | B6: 0 | C6: AA Rating --> | D6: https://dbrs.morningstar.com/research/424815/costco-wholesale-corporation-rating-report
A7: pre-tax Cost of Debt | B7: =(B4+B5+B6) -> 0.04547
A10: Cost of Equity
A11: Risk free rate | B11: 0.04067
A12: CRP | B12: ='Bottom-up Beta & CRP'!N20 -> 0.0016638544
A13: Beta | B13: ='Bottom-up Beta & CRP'!G70 -> 0.4572587
A14: Mature ERP | B14: 0.0433
A15: Cost of equity | B15: =B11+B13*(B14+B12) -> 0.061230114 | C15: https://pages.stern.nyu.edu/~adamodar/New_Home_Page/datafile/ctryprem.html
A18: Market Value of Equity
A19: Stock Price | B19: 925.08
A20: Shares Outstanding | B20: 443180000
A21: Market Value of Equity | B21: =B19*B20 -> 409976954400
A24: Market Value of Debt
A25: Book value of debt | B25: 5713000000 | C25: https://dbrs.morningstar.com/research/424815/costco-wholesale-corporation-rating-report
A26: Interest expense | B26: =154000 -> 154000 | C26: Costco 10k | D26: https://d18rn0p25nwr6d.cloudfront.net/CIK-0000909832/1d2e9494-f590-4908-8d5f-dac2a6a3f51d.pdf
A27: PMT (interest expense) | B27: =154000 -> 154000 | D27: Bond (Coupon) | E27: Age to maturity (years)
A28: FV (BV of debt) | B28: =B25 -> 5713000000 | D28: 1.6 | E28: =2027-2026+5/12 -> 1.4166667
A29: N | B29: =E32 -> 3.9583333 | D29: 3 | E29: =2027-2026+6/12 -> 1.5
A30: I/Y (cost of debt) | B30: =B7 -> 0.04547 | D30: 1.75 | E30: =2032-2026+5/12 -> 6.4166667
A31: MV of Debt (PV of above) | B31: =ABS(PV(B30,B29,B27,B28,1)) -> 4791531772 | D31: 1.375 | E31: =2032-2026+6/12 -> 6.5
A32: PV of Operating Lease | B32: 2668000000 | D32: Average | E32: =AVERAGE(E28:E31) -> 3.9583333
A33: MV of Debt (Adjusting for OL) | B33: =B31+B32 -> 7459531772
A36: WACC (Adjusted for OL)
A37: Cost of Debt | B37: =B7 -> 0.04547
A38: Cost of Equity | B38: =B15 -> 0.061230114
A39: MV Equity | B39: =B21 -> 409976954400
A40: MV Debt | B40: =B33 -> 7459531772
A41: WACC Adjusted for OL | B41: =B38*(B39/(B39+B40))+B37*(1-0.25)*(B40/(B39+B40)) -> 0.060745347 | D41: **We used a WACC of 6.052% for the TV and EV because we made minor changes to the wacc but everything was already made with the value of 6.052%
D60: Membership sample | E60: Overridable Raw Beta | F60: Current Market Cap | G60: Long Term Debt | H60: Short Term Debt | I60: D/E Ratio
D61: AAPL US Equity | E61: 1.1416803 | F61: 4033205.6 | G61: 89931 | H61: 22446 | I61: 0.027862949
D62: NFLX US Equity | E62: 1.1549887 | F62: 489084.57 | G62: 15782.039 | H62: 2212.935 | I62: 0.036793175
D63: AMZN US Equity | E63: 1.3789916 | F63: 2539781.5 | G63: 130900 | H63: 16938 | I63: 0.058208944
D64: SPOT US Equity | E64: 0.96869305 | F64: 134541.76 | G64: 2001 | H64: 75 | I64: 0.015430153
D65: PLNT US Equity | E65: 0.62604633 | F65: 8924.9584 | G65: 2553.373 | H65: 59.531 | I65: 0.29276372
D66: MSFT US Equity | E66: 0.99679124 | F66: 3740641.4 | G66: 100589 | H66: 11595 | I66: 0.029990579
D67: DBX US Equity | E67: 0.83242808 | F67: 7865.6754 | G67: 2798.4 | H67: 198.2 | I67: 0.38097174
D68: SAP US Equity | E68: 0.97656539 | F68: 309411.08 | G68: 6761 | H68: 3990 | I68: 0.034746655
D69: UBER US Equity | E69: 1.2876592 | F69: 190703.27 | G69: 9975 | H69: 311 | I69: 0.053937197
D70: ADBE US Equity | E70: 1.0633193 | F70: 139644.96 | G70: 4482 | H70: 1574 | I70: 0.043367122
D71: DIS US Equity | E71: 0.82211465 | F71: 192114.93 | G71: 35315 | H71: 6711 | I71: 0.21875447
D72: GOOGL US Equity | E72: 1.0641985 | F72: 3364709.6 | G72: 22574 | H72: 3122 | I72: 0.007636915
... D78: WMT US Equity | E78: 0.72748757 | F78: 817536.15 | G78: 52149 | H78: 7965 | I78: 0.073530693
D79: Average | E79: =AVERAGE(E61:E78) -> 1.0289277 | I79: =AVERAGE(I61:I78) -> 0.16171338

Sheet FCFF
F1: Adjustment R&D | G1: None | K1: Company | N1: Effective Tax Rate | O1: INCOME TAX | P1: INCOME BEOFRE INCOME TAX | Q1: INCOME TAX (BEFORE DEFERRALS)
A2: Current Year FCFF - Costco Wholesale | K2: Costco | N2: =O2/P2 -> 0.25134036 | O2: =2719 -> 2719 | P2: =10818 -> 10818 | Q2: =1395+449+955 -> 2799
A3: (amounts in thousands)
A4: EBIT | B4: =10383000 -> 10383000 | C4: https://ca.finance.yahoo.com/quote/COST/financials/
A5: Effective Tax Rate | B5: =N2 -> 0.25134036
A6: Risk free rate | B6: 0.04067 | C6: CNBC US 10Y Treasury as of Nov 12 2025
A7: Company Default spread | B7: 0.0048 | C7: As of Tues, Nov 11 2025 | D7: https://fred.stlouisfed.org/series/BAMLC0A2CAA#:~:text=Rates%20%3E%20Corporate%20Bonds-,ICE%20BofA%20AA%20US%20Corporate%20Index%20Option%2DAdjusted%20Spread%20(BAMLC0A2CAA,Release%20Date:%20Nov%2011%2C%202025
A8: Country Default Spread | B8: 0 | C8: AA Rating --> | D8: https://dbrs.morningstar.com/research/424815/costco-wholesale-corporation-rating-report
A9: pre-tax Cost of Debt | B9: =(B6+B7+B8) -> 0.04547
A11: Current Operational Lease expense | B11: =271000 -> 271000
A12: Life of the Operational Lease | B12: =20 -> 20
A13: Unadjusted Book Value of Debt | B13: =5805*1000 -> 5805000
A14: Current R&D Expense | B14: 0
A15: Amortizable Life for the R&D | B15: 0
A16: Adjusted EBIT (Due to OL & R&D) | B16: =B4+(B11-E32) -> 10519600
A17: Final Adjustment on EBIT (1-T) | B17: =B16*(1-B5) -> 7875600 | D17: capex
A18: Capital expenditure | B18: =5498*1000 -> 5498000 | D18: https://d18rn0p25nwr6d.cloudfront.net/CIK-0000909832/1d2e9494-f590-4908-8d5f-dac2a6a3f51d.pdf | E18: Operation Lease Adjustment - 2025
A19: Depreciation & Amortization | B19: =2426*1000 -> 2426000 | D19: https://d18rn0p25nwr6d.cloudfront.net/CIK-0000909832/1d2e9494-f590-4908-8d5f-dac2a6a3f51d.pdf
A20: Adjustement on CapEx | B20: =B18-B19 -> 3072000
A21: Inventory n-1 | B21: =18647*1000 -> 18647000
A22: Inventory n | B22: =18116*1000 -> 18116000
A23: A/R n-1 | B23: =2721*1000 -> 2721000 | C23: As of August 31, 2025, future minimum payments during the next five fiscal years and thereafter are as follows
A24: A/R n | B24: =3203*1000 -> 3203000
A25: A/P n-1 | B25: =19421*1000 -> 19421000
A26: A/P n | B26: =19783*1000 -> 19783000
A27: Non Cash NWC n-1 | B27: =(B21+B23)-B25 -> 1947000
A28: Non Cash NWC n | B28: =(B22+B24)-B26 -> 1536000
A29: change in NWC | B29: =B28-B27 -> -411000
A30: FCFF | B30: =B17-B20-B29 -> 5214600
C32: Depreciation of OL | E32: =(2688/B12)*1000 -> 134400

Sheet Bottom-up Beta & CRP
C4: Industry Bottom-up Beta Sample (shortened) | K4: Revenue Weighted CRP | Q4: Finding Weights of international countries using number of stores as a reference
C5: Ticker | D5: Beta | E5: Net Debt | F5: Total Equity | G5: net D/E | H5: Effective Tax Rate | K5: Country | L5: CDS | M5: Weight (revenue) | N5: Weighted CRP | Q5: Country | R5: # of stores | S5: Int Weight | T5: Weight
D6: Overridable Raw Beta | E6: Net Debt | F6: Total Equity | G6: net D/E | H6: Effective Tax Rate | K6: United states | L6: 0 | M6: 0.724 | N6: =L6*M6 -> 0 | Q6: United states | R6: 617 | T6: 0.724
C7: WMT US Equity | D7: 0.81860906 | E7: 51077 | F7: 97692 | G7: =E7/F7 -> 0.52283708 | H7: 0.23383633 | K7: Canada | L7: 0 | M7: 0.137 | N7: =L7*M7 -> 0 | Q7: Canada | R7: 109 | T7: 0.137
C8: TGT US Equity | D8: 0.75077498 | E8: 15113 | F8: 14666 | G8: =E8/F8 -> 1.0304787 | H8: 0.22239118 | K8: Mexico | L8: 0.0254 | M8: 0.033327485 | N8: =L8*M8 -> 0.00084651813 | Q8: Mexico | R8: 41 | S8: =R8/$R$20 -> 0.23976608 | T8: =S8*$N$33 -> 0.033327485
C9: DG US Equity | D9: 0.2192813 | E9: 16530.809 | F9: 7413.707 | G9: =E9/F9 -> 2.2297629 | H9: 0.21844079 | K9: Japan | L9: 0.0094 | M9: 0.029263158 | N9: =L9*M9 -> 0.00027507368 | Q9: Japan | R9: 36 | S9: =R9/$R$20 -> 0.21052632 | T9: =S9*$N$33 -> 0.029263158
C10: BJ US Equity | D10: 0.42451152 | E10: 2752.025 | F10: 1847.454 | G10: =E10/F10 -> 1.4896311 | H10: 0.25862631 | K10: The United Kingdom | L10: 0.008 | M10: 0.023573099 | N10: =L10*M10 -> 0.0001885848 | Q10: The United Kingdom | R10: 29 | S10: =R10/$R$20 -> 0.16959064 | T10: =S10*$N$33 -> 0.023573099
C11: FIVE US Equity | D11: 1.4568803 | E11: 1452.776 | F11: 1808.327 | G11: =E11/F11 -> 0.80338125 | H11: 0.25114494 | K11: South Korea | L11: 0.0066 | M11: 0.015444444 | N11: =L11*M11 -> 0.00010193333 | Q11: South Korea | R11: 19 | S11: =R11/$R$20 -> 0.11111111 | T11: =S11*$N$33 -> 0.015444444
C12: OLLI US Equity | D12: 0.81088489 | E12: 136.201 | F12: 1695.31 | G12: =E12/F12 -> 0.080339879 | H12: 0.24848955 | K12: Australia | L12: 0 | M12: 0.012192982 | N12: =L12*M12 -> 0 | Q12: Australia | R12: 15 | S12: =R12/$R$20 -> 0.087719298 | T12: =S12*$N$33 -> 0.012192982
C13: PSMT US Equity | D13: 0.72511983 | E13: 14.847 | F13: 1247.372 | G13: =E13/F13 -> 0.011902624 | H13: 0.28386231 | K13: Taiwan | L13: 0.008 | M13: 0.011380117 | N13: =L13*M13 -> 9.1040936e-05 | Q13: Taiwan | R13: 14 | S13: =R13/$R$20 -> 0.081871345 | T13: =S13*$N$33 -> 0.011380117
C14: L CN Equity | D14: 0.5372927 | E14: 17074 | F14: 11266 | G14: =E14/F14 -> 1.5155335 | H14: 0.26160338 | K14: China | L14: 0.0094 | M14: 0.0056900585 | N14: =L14*M14 -> 5.348655e-05 | Q14: China | R14: 7 | S14: =R14/$R$20 -> 0.040935673 | T14: =S14*$N$33 -> 0.0056900585
C15: MRU CN Equity | D15: 0.5009337 | E15: 4281.1 | F15: 7038.9 | G15: =E15/F15 -> 0.60820583 | H15: 0.22776852 | K15: Spain | L15: 0.0213 | M15: 0.0040643275 | N15: =L15*M15 -> 8.6570175e-05 | Q15: Spain | R15: 5 | S15: =R15/$R$20 -> 0.029239766 | T15: =S15*$N$33 -> 0.0040643275
C16: DLTR US Equity | D16: 0.76360935 | E16: 6574.1 | F16: 3977.4 | G16: =E16/F16 -> 1.6528637 | H16: 0.24653079 | K16: France | L16: 0.008 | M16: 0.001625731 | N16: =L16*M16 -> 1.3005848e-05 | Q16: France | R16: 2 | S16: =R16/$R$20 -> 0.011695906 | T16: =S16*$N$33 -> 0.001625731
C17: EMP/A CN Equity | D17: 0.4307639 | E17: 7179 | F17: 5544 | G17: =E17/F17 -> 1.2949134 | H17: 0.25025126 | K17: New Zealand | L17: 0 | M17: 0.0008128655 | N17: =L17*M17 -> 0 | Q17: New Zealand | R17: 1 | S17: =R17/$R$20 -> 0.0058479532 | T17: =S17*$N$33 -> 0.0008128655
C18: TSCO LN Equity | D18: 0.6844925 | E18: 10037 | F18: 11662 | G18: =E18/F18 -> 0.86065855 | H18: 0.2758465 | K18: Sweden | L18: 0 | M18: 0.0008128655 | N18: =L18*M18 -> 0 | Q18: Sweden | R18: 1 | S18: =R18/$R$20 -> 0.0058479532 | T18: =S18*$N$33 -> 0.0008128655
C19: SBRY LN Equity | D19: 0.9304859 | E19: 3832 | F19: 6651 | G19: =E19/F19 -> 0.57615396 | H19: 0.3236715 | K19: Iceland | L19: 0.0094 | M19: 0.0008128655 | N19: =L19*M19 -> 7.6409357e-06 | Q19: Iceland | R19: 1 | S19: =R19/$R$20 -> 0.0058479532 | T19: =S19*$N$33 -> 0.0008128655
C20: JMT PL Equity | D20: 0.9298818 | E20: 2658 | F20: 3253 | G20: =E20/F20 -> 0.81709192 | H20: 0.24253731 | K20: Total | M20: =SUM(M6:M19) -> 1 | N20: =SUM(N6:N19) -> 0.0016638544 | Q20: International Sum | R20: =sum(R8:R19) -> 171 | S20: =SUM(S6:S19) -> 1 | T20: =SUM(T6:T19) -> 1
C21: DIA SM Equity | D21: 0.4786263 | E21: 801.957 | F21: -37.682 | G21: 0 | H21: 0.25395105 | K21: https://pages.stern.nyu.edu/~adamodar/New_Home_Page/datafile/ctryprem.html
C22: AXFO SS Equity | D22: 0.3599856 | E22: 14559 | F22: 7388 | G22: =E22/F22 -> 1.970628 | H22: 0.23084922
C23: DNP PW Equity | D23: 0.9723535 | E23: 193.73 | F23: 7102.434 | G23: =E23/F23 -> 0.027276565 | H23: 0.16048168
C24: COLR BB Equity | D24: -0.002881366 | E24: 270.5 | F24: 3171.9 | G24: =E24/F24 -> 0.085280116 | H24: 0.25206889
C25: SON PL Equity | D25: 0.8267954 | E25: 3324.357 | F25: 3740.852 | G25: =E25/F25 -> 0.88866306 | H25: 0.13272933
C26: 8267 JT Equity | D26: 0.4647725 | E26: 1711644 | F26: 2135271 | G26: =E26/F26 -> 0.80160504 | H26: 0.56420861
C27: 7532 JP Equity | D27: 0.6868883 | E27: 270630 | F27: 624044 | G27: =E27/F27 -> 0.43367134 | H27: 0.33275875
C28: 023530 KS Equity | D28: 0.6493115 | E28: 11744180 | F28: 17033617 | G28: =E28/F28 -> 0.68947071 | H28: N/A
C29: CRC TB Equity | D29: 1.234346 | E29: 125314.41 | F29: 72380.59 | G29: =E29/F29 -> 1.7313262 | H29: 0.23453032 | M29: Costco reported Revenue Weights
C30: 6808 HK Equity | D30: 1.012604 | E30: -5893 | F30: 20428 | G30: 0 | H30: 0.62524272 | M30: Regions | N30: Weight
C31: COL AU Equity | D31: 0.6273057 | E31: 9472 | F31: 3806 | G31: =E31/F31 -> 2.488702 | H31: 0.29752604 | M31: US | N31: 0.724
C32: MTS AU Equity | D32: 0.7163421 | E32: 1806 | F32: 1636.6 | G32: =E32/F32 -> 1.1035073 | H32: 0.2654225 | M32: Canada | N32: 0.137
C33: WALMEX* MM Equity | D33: 1.034831 | E33: 43216.322 | F33: 232875.5 | G33: =E33/F33 -> 0.18557694 | H33: 0.21911761 | M33: Other | N33: 0.139
C34: SORIANAB MM Equity | D34: 0.4518577 | E34: 19812 | F34: 82615 | G34: =E34/F34 -> 0.23981117 | H34: 0.28380359
C35: EXITO CB Equity | D35: 0.4838082 | E35: 2896983 | F35: 8015512 | G35: =E35/F35 -> 0.36142208 | H35: 0.19004261
C36: ROST US Equity | D36: 0.81227529 | E36: 951.685 | F36: 5509.195 | G36: =E36/F36 -> 0.17274484 | H36: 0.24170721
C37: TJX US Equity | D37: 0.65556318 | E37: 7443 | F37: 8393 | G37: =E37/F37 -> 0.88681044 | H37: 0.24973006
C38: GO US Equity | D38: 0.77379018 | E38: 1593.798 | F38: 1197.384 | G38: =E38/F38 -> 1.3310667 | H38: 0.29741326
C39: IMKTA US Equity | D39: 0.5421021 | E39: 211.26712 | F39: 1545.749 | G39: =E39/F39 -> 0.13667621 | H39: 0.23963507
C40: WMK US Equity | D40: 0.44402602 | E40: -239.954 | F40: 1446.031 | G40: 0 | H40: 0.26840126
C41: SPTN US Equity | D41: 0.60374385 | E41: 1086.85 | F41: 743.49 | G41: =E41/F41 -> 1.4618219 | H41: 0.97287982
C42: BIMAS TI Equity | D42: 1.084753 | E42: 29213.193 | F42: 148682.6 | G42: =E42/F42 -> 0.19648024 | H42: 0.28228348
C43: MGROS TI Equity | D43: 0.9367681 | E43: -5341.145 | F43: 63486.76 | G43: 0 | H43: 0.17669408
C44: KESKOB FH Equity | D44: 0.6625617 | E44: 2908.2 | F44: 2734.9 | G44: =E44/F44 -> 1.0633661 | H44: 0.19490986
C45: CHDRAUIB MM Equity | D45: 0.8055499 | E45: 52576.993 | F45: 49280.39 | G45: =E45/F45 -> 1.0668948 | H45: 0.30519997
C46: LACOMUBC MM Equity | D46: 0.9033679 | E46: -703.785 | F46: 30700.98 | G46: 0 | H46: 0.22625256
C47: CA FP Equity | D47: 0.6808661 | E47: 8948 | F47: 12484 | G47: =E47/F47 -> 0.71675745 | H47: 0.27813358
C48: BGFV US Equity | D48: 1.3685741 | E48: 293.72 | F48: 175.611 | G48: =E48/F48 -> 1.6725604 | H48: N/A
C49: SFM US Equity | D49: 0.75993359 | E49: 1414.082 | F49: 1321.893 | G49: =E49/F49 -> 1.0697401 | H49: 0.24886027
C50: KR US Equity | D50: 0.29787928 | E50: 21123 | F50: 8281 | G50: =E50/F50 -> 2.5507789 | H50: 0.20047876
C51: AD NA Equity | D51: 0.5040535 | E51: 13823 | F51: 15454 | G51: =E51/F51 -> 0.89446098 | H51: 0.21692169
C52: 139480 KS Equity | D52: 0.6318773 | E52: 10364318 | F52: 13184076 | G52: =E52/F52 -> 0.78612396 | H52: N/A
C53: WES AU Equity | D53: 1.093476 | E53: 10530 | F53: 9189 | G53: =E53/F53 -> 1.1459354 | H53: 0.27806563
C54: CENCOSUD CI Equity | D54: 0.9220484 | E54: 4784161.8 | F54: 5311297 | G54: =E54/F54 -> 0.90075207 | H54: 0.51464822
C55: Average | D55: =AVERAGE(D7:D54) -> 0.71799329 | G55: =AVERAGE(G7:G54) -> 0.84486803 | H55: =AVERAGE(H7:H54) -> 0.28399885
E60: Industry | F60: Average Beta | G60: Average D/E | H60: Marginal Tax Rate | I60: Weight | J60: Unlevered Beta
E61: Sales | F61: =D55 -> 0.71799329 | G61: 0.84 | H61: =H55 -> 0.28399885 | I61: 0.981 | J61: =F61/(1+(1-H61)*G61) -> 0.44834203
E62: Membership | F62: 1.0289277 | G62: 0.1617 | H62: 0.25 | I62: 0.019 | J62: =F62/(1+(1-H62)*G62) -> 0.91764079
F65: BV Net Debt | G65: 0
F66: BV Equity | G66: 23622000000
F67: Costco Net D/E | G67: =G65/G66 -> 0
F68: Tax Rate | G68: 0.25
F69: Unlevered Beta | G69: =J61*I61+J62*I62 -> 0.4572587
F70: Levered Beta | G70: =G69*(1+(1-G68)*G67) -> 0.4572587

Sheet TV & EV
A2: Growth Rate
A4: Expected Growth Rate = Reinvestment Rate * Return on Capital
A5: Reinvestment Rate = (Net Capital Expenditure + Change in Non-Cash Working Capital) / After-Tax Operating Income
A6: Return on Capital (ROC) = After-Tax Operating Income / (Book Value of Debt + Book Value of Equity - Cash)
A8: Expected Growth Rate | C8: (in thousands)
A9: All in thousands
A10: After-tax OI | B10: =FCFF!B17 -> 7875600
A11: Reinvestment | B11: =FCFF!B20+FCFF!B29 -> 2661000
A12: Reinvestment Rate | B12: =B11/B10 -> 0.33787902
G13: Excess Cash = total cash and cash equivalents - Operational cash | U13: Net cash provided by operating activities: $ 13,335
A14: Adjusted book value of debt | B14: =(5805000)+2668000 -> 8473000 | C14: 10-k | D14: long term debt excluding current portion | E14: add PV OL | G14: =14161000-13335000 -> 826000
A15: Book value of Equity | B15: 29164000 | C15: 10-k balance sheet | D15: total equity
A16: Excess Cash | B16: =G14 -> 826000 | C16: 10-k balance sheet
A17: Invested capital | B17: =B14+B15-B16 -> 36811000
A19: ROIC | B19: =B10/B17 -> 0.21394692
A21: g | B21: =B19*B12 -> 0.072288175 | D21: High growth period
A24: Growth rate
A25: Risk free rate | B25: =FCFF!B6 -> 0.04067
A26: Stable growth | B26: =B25+0.01 -> 0.05067
A27: TERMINAL VALUE
A29: High-growth period | B29: 5 years
A30: FCFF at year 5 | B30: =(FCFF!B30*(1+FCFF!B6)^5) -> 6364820.7 | C30: FCFF*(1+stable g)
A31: Growth rate high-growth period g1 | B31: =B21 -> 0.072288175
B32: =(B31-B26)/5 -> 0.0043236349 | E32: Different g
E33: g1 | F33: =B31 -> 0.072288175
A34: g stable | B34: =B26 -> 0.05067 | E34: g2 | F34: =F33-B32 -> 0.06796454
A35: WACC | B35: 0.06052 | E35: g3 | F35: =F34-B32 -> 0.063640905
E36: g4 | F36: =F35-B32 -> 0.05931727
A37: Numerator: | B37: =B30*(1+B26) -> 6687326.1 | E37: g5 | F37: =F36-B32 -> 0.054993635
A38: Denominator | B38: =B35-B34 -> 0.00985
A40: TV | B40: =B37/B38 -> 678916360
A41: PV TV | B41: =B40/(1+B35)^5 -> 5.0608324e+08 | C41: (in Thousands)
A46: Entreprise Value
H47: FCFF₁ = FCFF₀ × (1 + High-Growth Rate)
B48: FCFF0 | C48: FCFF1 | D48: FCFF2 | E48: FCFF3 | F48: FCFF4 | G48: FCFF5
A49: Value | B49: =FCFF!B30 -> 5214600 | C49: =B49*(1+F33) -> 5591553.9 | D49: =C49*(1+F34) -> 5971581.3 | E49: =D49*(1+F35) -> 6351618.1 | F49: =E49*(1+F36) -> 6728378.7 | G49: =F49*(1+F37) -> 7098396.7
A50: PV | B50: =B49 -> 5214600 | C50: =C49/(1+B35)^1 -> 5272464.3 | D50: =D49/(1+B35)^2 -> 5309475.5 | E50: =E49/(1+B35)^3 -> 5325100.2 | F50: =F49/(1+B35)^4 -> 5319061.1 | G50: =G49/(1+B35)^5 -> 5291343.5
A51: Sum | B51: =C50+D50+E50+F50+G50 -> 26517445
A53: Entreprise Value | B53: =B51+B41 -> 5.3260069e+08 | C53: (in Thousands)
A55: OVERVALUED OR UNDERVALUED?
A57: Market Value of Debt | B57: Clean Equity | C57: Shares outstanding | D57: Intrisic Share Value | E57: Share price
A58: =WACC!B31 -> 4791531772 | B58: =B53*1000-A58 -> 527809156767 | C58: =WACC!B20 -> 443180000 | D58: =B58/C58 -> 1190.9589 | E58: =WACC!B19 -> 925.08
A62: Entreprise Value | B62: =B53*1000 -> 532600688539
A63: Market Value of Debt (adjusted for OL) | B63: =WACC!B33 -> 7459531772
A64: Fundamental Equity Value | B64: =B62-B63 -> 525141156767
A65: Market Cap | B65: =C58*E58 -> 409976954400
A66: Undervalued | B66: =(B65-B64)/B65 -> -0.28090409

Sheet Sensitivity 
B1: Sensitivity Analysis – Costco DCF: WACC vs High-Growth OI Rate
C2: WACC
B3: High Growth period Rate (g) | D3: =J4*0.96 -> 0.058464 | E3: =J4*0.98 -> 0.059682 | F3: =J4*1.02 -> 0.062118 | G3: =J4*1.04 -> 0.063336 | I3: High-growth FCFF growth 1 | J3: 0.0723 | L3: g stable | M3: ='TV & EV'!B26 -> 0.05067
C4: =-J3*0.96 -> -0.069408 | D4: -0.6214 | E4: -0.4004 | F4: -0.0996 | G4: 0.0074 | I4: WACC | J4: 0.0609
C5: =-J3*0.98 -> -0.070854 | D5: -0.622 | E5: -0.4007 | F5: -0.0998 | G5: 0.0071
C6: =-J3*1.02 -> -0.073746 | D6: -0.6221 | E6: -0.4012 | F6: -0.1003 | G6: 0.0067 | I6: FCFF5 | J6: ='TV & EV'!B30 -> 6364820.7
C7: =-J3*1.04 -> -0.075192 | D7: -0.6223 | E7: -0.4014 | F7: -0.1005 | G7: 0.0065
I8: Numerator: | J8: =6687326.15 -> 6687326.2
I9: Denominator | J9: =G3-M3 -> 0.012666
I11: TV | J11: =J8/J9 -> 5.2797459e+08
B12: New Growth Rates | I12: PV TV | J12: =J11/(1+G3)^5 -> 3.883832e+08
C13: 0.96 | D13: 0.98 | E13: 1.02 | F13: 1.04
B14: g1 | C14: ='TV & EV'!F33*0.96 -> 0.069396648 | D14: ='TV & EV'!F33*0.98 -> 0.070842411 | E14: ='TV & EV'!F33*1.02 -> 0.073733938 | F14: ='TV & EV'!F33*1.04 -> 0.075179702
B15: g2 | C15: ='TV & EV'!F34*0.96 -> 0.065245958 | D15: ='TV & EV'!F34*0.98 -> 0.066605249 | E15: ='TV & EV'!F34*1.02 -> 0.069323831 | F15: ='TV & EV'!F34*1.04 -> 0.070683121 | J15: FCFF0 | K15: FCFF1 | L15: FCFF2 | M15: FCFF3 | N15: FCFF4 | O15: FCFF5
B16: g3 | C16: ='TV & EV'!F35*0.96 -> 0.061095269 | D16: ='TV & EV'!F35*0.98 -> 0.062368087 | E16: ='TV & EV'!F35*1.02 -> 0.064913723 | F16: ='TV & EV'!F35*1.04 -> 0.066186541 | I16: Value | J16: =FCFF!B30 -> 5214600 | K16: =J16*(1+F14) -> 5606632 | L16: =K16*(1+F15) -> 6002926.3 | M16: =L16*(1+F16) -> 6400239.2 | N16: =M16*(1+F17) -> 6795069.7 | O16: =N16*(1+F18) -> 7183702.7
B17: g4 | C17: ='TV & EV'!F36*0.96 -> 0.056944579 | D17: ='TV & EV'!F36*0.98 -> 0.058130924 | E17: ='TV & EV'!F36*1.02 -> 0.060503615 | F17: ='TV & EV'!F36*1.04 -> 0.061689961 | I17: PV | J17: =FCFF!B30 -> 5214600 | K17: =K16/(1+G3) -> 5272681.5 | L17: =L16/(1+G3)^2 -> 5309113.1 | M17: =M16/(1+G3)^3 -> 5323345.5 | N17: =N16/(1+G3)^4 -> 5315105 | O17: =O16/(1+G3)^5 -> 5284401
B18: g5 | C18: ='TV & EV'!F37*0.96 -> 0.05279389 | D18: ='TV & EV'!F37*0.98 -> 0.053893762 | E18: ='TV & EV'!F37*1.02 -> 0.056093508 | F18: ='TV & EV'!F37*1.04 -> 0.05719338 | I18: Sum | J18: =K17+L17+M17+N17+O17 -> 26504646
I20: Entreprise Value | J20: =J12+J18 -> 4.1488784e+08 | K20: (in Thousands)
B23: OVERVALUED OR UNDERVALUED?
B24: Market Value of Debt | C24: Clean Equity | D24: Shares outstanding | E24: Intrisic Share Value | F24: Share price
B25: ='TV & EV'!A58 -> 4791531772 | C25: =(J20*1000)-B25 -> 410096312537 | D25: ='TV & EV'!C58 -> 443180000 | E25: =C25/D25 -> 925.34932 | F25: ='TV & EV'!E58 -> 925.08
B29: Enterprice Value | C29: =J20*1000 -> 414887844309
B30: Market Value of Debt (adjusted for OL) | C30: ='TV & EV'!B63 -> 7459531772
B31: Fundamental Equity Value | C31: =C29-C30 -> 407428312537
B32: Market Cap | C32: ='TV & EV'!B65 -> 409976954400
B33: Overvalued | C33: =(C31-C32)/C32 -> -0.0062165491

Sheet Operating Leverage
A2: Company | B2: 2022 | C2: 2023 | D2: 2024 | E2: 2025 (TTM) | F2: Source
A3: Walmart
A4: EBIT (in billions) | B4: 25.94 | C4: 20.43 | D4: 27.01 | E4: 28.98
A5: % change | C5: =((C4-B4)/B4) -> -0.21241326 | D5: =((D4-C4)/C4) -> 0.32207538 | E5: =((E4-D4)/D4) -> 0.07293595
A6: Revenue (in billions) | B6: 572.75 | C6: 611.29 | D6: 648.13 | E6: 693.15
A7: % change | C7: =(C6-B6)/B6 -> 0.067289393 | D7: =(D6-C6)/C6 -> 0.060265995 | E7: =(E6-D6)/D6 -> 0.069461373
A8: Degree of Operating Leverage | C8: =C5/C7 -> -3.1567124 | D8: =D5/D7 -> 5.3442307 | E8: =E5/E7 -> 1.0500217
A10: Target
A11: EBIT (in billions) | B11: 9.328 | C11: 3.896 | D11: 5.799 | E11: 5.524
A12: % change | C12: =((C11-B11)/B11) -> -0.58233276 | D12: =((D11-C11)/C11) -> 0.48844969 | E12: =((E11-D11)/D11) -> -0.047421969
A13: Revenue (in billions) | B13: 106.005 | C13: 109.12 | D13: 107.412 | E13: 105.64
A14: % change | C14: =(C13-B13)/B13 -> 0.029385406 | D14: =(D13-C13)/C13 -> -0.015652493 | E14: =(E13-D13)/D13 -> -0.016497226
A15: Degree of Operating Leverage | C15: =C12/C14 -> -19.817074 | D15: =D12/D14 -> -31.205873 | E15: =E12/E14 -> 2.8745421
A17: Dollarama
A18: EBIT (in billions) | B18: 0.9823 | C18: 1.1976 | D18: 1.5181 | E18: 1.8654
A19: % change | C19: =((C18-B18)/B18) -> 0.21917948 | D19: =((D18-C18)/C18) -> 0.26761857 | E19: =((E18-D18)/D18) -> 0.22877281
A20: Revenue (in billions) | B20: 4.33 | C20: 5.0527 | D20: 5.8673 | E20: 6.689
A21: % change | C21: =(C20-B20)/B20 -> 0.16690531 | D21: =(D20-C20)/C20 -> 0.16122073 | E21: =(E20-D20)/D20 -> 0.14004738
A22: Degree of Operating Leverage | C22: =C19/C21 -> 1.3131965 | D22: =D19/D21 -> 1.6599513 | E22: =E19/E21 -> 1.6335386
A24: Dollar General
A25: EBIT (in billions) | B25: 3.2206 | C25: 3.3283 | D25: 2.4463 | E25: 1.7895
A26: % change | C26: =((C25-B25)/B25) -> 0.033440974 | D26: =((D25-C25)/C25) -> -0.26500015 | E26: =((E25-D25)/D25) -> -0.2684871
A27: Revenue (in billions) | B27: 34.2204 | C27: 37.8448 | D27: 38.6916 | E27: 41.6516
A28: % change | C28: =(C27-B27)/B27 -> 0.10591343 | D28: =(D27-C27)/C27 -> 0.022375597 | E28: =(E27-D27)/D27 -> 0.076502393
A29: Degree of Operating Leverage | C29: =C26/C28 -> 0.31573874 | D29: =D26/D28 -> -11.843266 | E29: =E26/E28 -> -3.5095255
A31: Dollar Tree
A32: EBIT (in billions) | B32: 1.8114 | C32: 2.0993 | D32: 1.7745 | E32: 1.4794
A33: % change | C33: =((C32-B32)/B32) -> 0.15893784 | D33: =((D32-C32)/C32) -> -0.15471824 | E33: =((E32-D32)/D32) -> -0.16630037
A34: Revenue (in billions) | B34: 26.3212 | C34: 15.4115 | D34: 16.7811 | E34: 18.5511
A35: % change | C35: =(C34-B34)/B34 -> -0.41448338 | D35: =(D34-C34)/C34 -> 0.088868702 | E35: =(E34-D34)/D34 -> 0.1054758
A36: Degree of Operating Leverage | C36: =C33/C35 -> -0.3834601 | D36: =D33/D35 -> -1.7409756 | E36: =E33/E35 -> -1.5766684
A38: Loblaws
A39: EBIT (in billions) | B39: 3.133 | C39: 3.375 | D39: 3.738 | E39: 4.396
A40: % change | C40: =((C39-B39)/B39) -> 0.07724226 | D40: =((D39-C39)/C39) -> 0.10755556 | E40: =((E39-D39)/D39) -> 0.17602996
A41: Revenue (in billions) | B41: 53.17 | C41: 56.504 | D41: 59.5299 | E41: 63.15
A42: % change | C42: =(C41-B41)/B41 -> 0.062704533 | D42: =(D41-C41)/C41 -> 0.053551961 | E42: =(E41-D41)/D41 -> 0.060811458
A43: Degree of Operating Leverage | C43: =C40/C42 -> 1.2318449 | D43: =D40/D42 -> 2.0084336 | E43: =E40/E42 -> 2.8946841
A45: Kroger
A46: EBIT (in billions) | B46: 2.622 | C46: 3.437 | D46: 3.277 | E46: 4
A47: % change | C47: =((C46-B46)/B46) -> 0.31083143 | D47: =((D46-C46)/C46) -> -0.046552226 | E47: =((E46-D46)/D46) -> 0.22062862
A48: Revenue (in billions) | B48: 137.888 | C48: 148.258 | D48: 150.039 | E48: 147
A49: % change | C49: =(C48-B48)/B48 -> 0.075205964 | D49: =(D48-C48)/C48 -> 0.012012842 | E49: =(E48-D48)/D48 -> -0.020254734
A50: Degree of Operating Leverage | C50: =C47/C49 -> 4.1330688 | D50: =D47/D49 -> -3.8752049 | E50: =E47/E49 -> -10.892694
A52: Albertsons
A53: EBIT (in billions) | B53: 2.5611 | C53: 2.3918 | D53: 2.0814 | E53: 1.6158
A54: % change | C54: =((C53-B53)/B53) -> -0.066104408 | D54: =((D53-C53)/C53) -> -0.12977674 | E54: =((E53-D53)/D53) -> -0.22369559
A55: Revenue (in billions) | B55: 71.887 | C55: 77.6497 | D55: 79.2377 | E55: 81.3706
A56: % change | C56: =(C55-B55)/B55 -> 0.080163312 | D56: =(D55-C55)/C55 -> 0.02045082 | E56: =(E55-D55)/D55 -> 0.026917742
A57: Degree of Operating Leverage | C57: =C54/C56 -> -0.82462172 | D57: =D54/D56 -> -6.3457964 | E57: =E54/E56 -> -8.3103399
A59: TJX
A60: EBIT (in billions) | B60: 4.517 | C60: 4.72 | D60: 6.046 | E60: 6.691
A61: % change | C61: =((C60-B60)/B60) -> 0.044941333 | D61: =((D60-C60)/C60) -> 0.2809322 | E61: =((E60-D60)/D60) -> 0.1066821
A62: Revenue (in billions) | B62: 48.55 | C62: 49.936 | D62: 54.217 | E62: 57.925
A63: % change | C63: =(C62-B62)/B62 -> 0.028547889 | D63: =(D62-C62)/C62 -> 0.085729734 | E63: =(E62-D62)/D62 -> 0.068391833
A64: Degree of Operating Leverage | C64: =C61/C63 -> 1.5742437 | D64: =D61/D63 -> 3.2769518 | E64: =E61/E63 -> 1.5598661
A66: Five Below
A67: EBIT (in billions) | B67: 0.3798 | C67: 0.345 | D67: 0.3855 | E67: 0.3493
A68: % change | C68: =((C67-B67)/B67) -> -0.091627172 | D68: =((D67-C67)/C67) -> 0.1173913 | E68: =((E67-D67)/D67) -> -0.093904021
A69: Revenue (in billions) | B69: 2.8483 | C69: 3.0763 | D69: 3.5593 | E69: 4.2319
A70: % change | C70: =(C69-B69)/B69 -> 0.080047748 | D70: =(D69-C69)/C69 -> 0.15700679 | E70: =(E69-D69)/D69 -> 0.18896974
A71: Degree of Operating Leverage | C71: =C68/C70 -> -1.1446565 | D71: =D68/D70 -> 0.74768296 | E71: =E68/E70 -> -0.49692623
A73: Carrefour SA | F73: https://ca.finance.yahoo.com/quote/CRRFY/financials/
A74: EBIT (in billions) | B74: 1.869 | C74: 2.556 | D74: 2.042 | E74: 1.587
A75: % change | C75: =((C74-B74)/B74) -> 0.36757624 | D75: =((D74-C74)/C74) -> -0.20109546 | E75: =((E74-D74)/D74) -> -0.22282076
A76: Revenue (in billions) | B76: 71.761 | C76: 83.088 | D76: 84.91 | E76: 88.54
A77: % change | C77: =(C76-B76)/B76 -> 0.1578434 | D77: =(D76-C76)/C76 -> 0.021928558 | E77: =(E76-D76)/D76 -> 0.042751148
A78: Degree of Operating Leverage | C78: =C75/C77 -> 2.3287401 | D78: =D75/D77 -> -9.1704828 | E78: =E75/E77 -> -5.2120416
A80: Tesco PLC | F80: https://ca.finance.yahoo.com/quote/TSCDY/financials/
A81: EBIT (in billions) | B81: 2.685 | C81: 1.527 | D81: 3.102 | E81: 2.888
A82: % change | C82: =((C81-B81)/B81) -> -0.43128492 | D82: =((D81-C81)/C81) -> 1.0314342 | E82: =((E81-D81)/D81) -> -0.06898775
A83: Revenue (in billions) | B83: 61.344 | C83: 65.322 | D83: 68.187 | E83: 71.179
A84: % change | C84: =(C83-B83)/B83 -> 0.064847418 | D84: =(D83-C83)/C83 -> 0.043859649 | E84: =(E83-D83)/D83 -> 0.043879332
A85: Degree of Operating Leverage | C85: =C82/C84 -> -6.6507647 | D85: =D82/D84 -> 23.516699 | E85: =E82/E84 -> -1.5722151
A87: Ahold Delhaize | F87: https://ca.finance.yahoo.com/quote/0RI8.IL/financials/
A88: EBIT (in billions) | B88: 3.338 | C88: 3.837 | D88: 3.035 | E88: 3.439
A89: % change | C89: =((C88-B88)/B88) -> 0.14949071 | D89: =((D88-C88)/C88) -> -0.20901746 | E89: =((E88-D88)/D88) -> 0.13311367
A90: Revenue (in billions) | B90: 75.6 | C90: 86.984 | D90: 88.734 | E90: 92.139
A91: % change | C91: =(C90-B90)/B90 -> 0.15058201 | D91: =(D90-C90)/C90 -> 0.020118643 | E91: =(E90-D90)/D90 -> 0.038373115
A92: Degree of Operating Leverage | C92: =C89/C91 -> 0.9927528 | D92: =D89/D91 -> -10.389243 | E92: =E89/E91 -> 3.4689306
A94: Rewe | F94: https://www.rewe-group.com/en/press-and-media/newsroom/press-releases/rewe-group-successfully-navigates-crisis-year-2022-and-stays-on-steady-course/?utm_source=chatgpt.com
A95: EBIT (in billions) | B95: 2.789 | C95: 3.105 | D95: 2.432 | E95: 2.806
A96: % change | C96: =((C95-B95)/B95) -> 0.11330226 | D96: =((D95-C95)/C95) -> -0.21674718 | E96: =((E95-D95)/D95) -> 0.15378289
A97: Revenue (in billions) | B97: 91.7 | C97: 99.9 | D97: 104 | E97: 92.139
A98: % change | C98: =(C97-B97)/B97 -> 0.089422028 | D98: =(D97-C97)/C97 -> 0.041041041 | E98: =(E97-D97)/D97 -> -0.11404808
A99: Degree of Operating Leverage | C99: =C96/C98 -> 1.2670509 | D99: =D96/D98 -> -5.2812301 | E99: =E96/E98 -> -1.3484041
A101: Metro Inc. | F101: https://ca.finance.yahoo.com/quote/MRU.TO/financials/
A102: EBIT (in billions) | B102: 1.2665 | C102: 1.2864 | D102: 1.4718 | E102: 1.4882
A103: % change | C103: =((C102-B102)/B102) -> 0.015712594 | D103: =((D102-C102)/C102) -> 0.14412313 | E103: =((E102-D102)/D102) -> 0.011142818
A104: Revenue (in billions) | B104: 18.8889 | C104: 20.7246 | D104: 21.2199 | E104: 21.8364
A105: % change | C105: =(C104-B104)/B104 -> 0.09718406 | D105: =(D104-C104)/C104 -> 0.023899134 | E105: =(E104-D104)/D104 -> 0.029052917
A106: Degree of Operating Leverage | C106: =C103/C105 -> 0.16167871 | D106: =D103/D105 -> 6.0304751 | E106: =E103/E105 -> 0.38353526
A108: Sainsbury | F108: https://ca.finance.yahoo.com/quote/SUY1.HA/financials/
A109: EBIT (in billions) | B109: - | C109: 0.636 | D109: 0.813 | E109: 0.957
A110: % change | C110: =((C109-B109)/B109) -> #VALUE! | D110: =((D109-C109)/C109) -> 0.27830189 | E110: =((E109-D109)/D109) -> 0.17712177
A111: Revenue (in billions) | B111: - | C111: 31.491 | D111: 32.238 | E111: 32.812
A112: % change | C112: =(C111-B111)/B111 -> #VALUE! | D112: =(D111-C111)/C111 -> 0.023721063 | E112: =(E111-D111)/D111 -> 0.017805075
A113: Degree of Operating Leverage | C113: =C110/C112 -> #VALUE! | D113: =D110/D112 -> 11.732269 | E113: =E110/E112 -> 9.9478252
A115: Marks & Spencer | F115: https://ca.finance.yahoo.com/quote/MA6.DU/financials/
A116: EBIT (in billions) | B116: 0.6053 | C116: 0.672 | D116: 0.8464 | E116: 0.6768
A117: % change | C117: =((C116-B116)/B116) -> 0.11019329 | D117: =((D116-C116)/C116) -> 0.25952381 | E117: =((E116-D116)/D116) -> -0.20037807
...

Sheet Market concentration
B2: Main Players | C2: U.S. Market Share
B3: Walmart Inc. | C3: 0.62
B4: Costco Wholesale Corp. | C4: 0.25
B5: Other Competitors | C5: 0.13

Sheet Membership Sample - Presentatio
C6: Levered Beta | D6: D/E Ratio
B7: AAPL US Equity | C7: 1.1416803 | D7: 0.027862949
B8: NFLX US Equity | C8: 1.1549887 | D8: 0.036793175
B9: AMZN US Equity | C9: 1.3789916 | D9: 0.058208944
B10: SPOT US Equity | C10: 0.96869305 | D10: 0.015430153
B11: PLNT US Equity | C11: 0.62604633 | D11: 0.29276372
B12: MSFT US Equity | C12: 0.99679124 | D12: 0.029990579
B13: DBX US Equity | C13: 0.83242808 | D13: 0.38097174
B14: SAP US Equity | C14: 0.97656539 | D14: 0.034746655
B15: UBER US Equity | C15: 1.2876592 | D15: 0.053937197
B16: ADBE US Equity | C16: 1.0633193 | D16: 0.043367122
B17: DIS US Equity | C17: 0.82211465 | D17: 0.21875447
B18: GOOGL US Equity | C18: 1.0641985 | D18: 0.007636915
... B24: WMT US Equity | C24: 0.72748757 | D24: 0.073530693
B25: Average | C25: =AVERAGE(C7:C24) -> 1.0289277 | D25: =AVERAGE(D7:D24) -> 0.16171338
